{
    "2011-07-15": "partly-cloudy-day",
    "2011-07-16": "Clear throughout the day.",
    "2011-07-17": "rain",
    "2011-07-18": "rain",
    "2011-07-22": "rain",
    "2011-07-23": "rain",
    "2011-07-24": "partly-cloudy-day",
    "2011-07-25": "partly-cloudy-day",
    "2011-08-05": "rain",
    "2011-08-06": "rain",
    "2011-08-07": "rain",
    "2011-08-08": "rain",
    "2011-08-12": "rain",
    "2011-08-13": "partly-cloudy-day",
    "2011-08-14": "rain",
    "2011-08-15": "rain",
    "2011-08-19": "rain",
    "2011-08-20": "Partly cloudy throughout the day.",
    "2011-08-21": "Clear throughout the day.",
    "2011-08-22": "partly-cloudy-day",
    "2011-08-26": "rain",
    "2011-08-27": "rain",
    "2011-08-28": "partly-cloudy-day",
    "2011-08-29": "rain",
    "2011-09-09": "rain",
    "2011-09-10": "rain",
    "2011-09-11": "rain",
    "2011-09-12": "rain",
    "2011-09-16": "partly-cloudy-day",
    "2011-09-17": "partly-cloudy-day",
    "2011-09-18": "rain",
    "2011-09-19": "rain",
    "2011-09-23": "partly-cloudy-day",
    "2011-09-24": "Clear throughout the day.",
    "2011-09-25": "Clear throughout the day.",
    "2011-09-26": "Clear throughout the day.",
    "2011-09-30": "Clear throughout the day.",
    "2011-10-01": "Clear throughout the day.",
    "2011-10-02": "Clear throughout the day.",
    "2011-10-03": "Clear throughout the day.",
    "2011-10-14": "Partly cloudy throughout the day.",
    "2011-10-15": "Clear throughout the day.",
    "2011-10-16": "rain",
    "2011-10-17": "Clear throughout the day.",
    "2011-10-21": "partly-cloudy-day",
    "2011-10-22": "Clear throughout the day.",
    "2011-10-23": "rain",
    "2011-10-28": "partly-cloudy-day",
    "2011-10-29": "Foggy in the morning.",
    "2011-10-30": "rain",
    "2011-10-31": "partly-cloudy-day",
    "2011-11-04": "Foggy in the morning.",
    "2011-11-05": "rain",
    "2011-11-06": "rain",
    "2011-11-07": "Clear throughout the day.",
    "2011-11-18": "rain",
    "2011-11-19": "partly-cloudy-day",
    "2011-11-20": "Clear throughout the day.",
    "2011-11-21": "Foggy overnight.",
    "2011-11-25": "rain",
    "2011-11-26": "rain",
    "2011-11-27": "partly-cloudy-day",
    "2011-11-28": "partly-cloudy-day",
    "2011-12-02": "rain",
    "2011-12-03": "rain",
    "2011-12-04": "partly-cloudy-day",
    "2011-12-05": "partly-cloudy-day",
    "2011-12-09": "rain",
    "2011-12-10": "rain",
    "2011-12-11": "partly-cloudy-day",
    "2011-12-12": "rain",
    "2011-12-13": "rain",
    "2011-12-16": "rain",
    "2011-12-17": "rain",
    "2011-12-18": "rain",
    "2011-12-19": "partly-cloudy-day",
    "2011-12-20": "partly-cloudy-day",
    "2011-12-21": "rain",
    "2011-12-22": "partly-cloudy-day",
    "2011-12-26": "rain",
    "2011-12-27": "partly-cloudy-day",
    "2011-12-30": "rain",
    "2011-12-31": "partly-cloudy-day",
    "2012-01-01": "rain",
    "2012-01-02": "rain",
    "2012-01-03": "rain",
    "2012-01-04": "rain",
    "2012-01-11": "partly-cloudy-day",
    "2012-01-14": "partly-cloudy-day",
    "2012-01-15": "partly-cloudy-day",
    "2012-01-16": "snow",
    "2012-01-20": "rain",
    "2012-01-21": "partly-cloudy-day",
    "2012-01-22": "rain",
    "2012-01-27": "partly-cloudy-day",
    "2012-01-28": "partly-cloudy-day",
    "2012-01-29": "Clear throughout the day.",
    "2012-01-31": "Clear throughout the day.",
    "2012-02-01": "Clear throughout the day.",
    "2012-02-03": "partly-cloudy-day",
    "2012-02-04": "partly-cloudy-day",
    "2012-02-05": "partly-cloudy-day",
    "2012-02-06": "Clear throughout the day.",
    "2012-02-10": "partly-cloudy-day",
    "2012-02-11": "partly-cloudy-day",
    "2012-02-12": "partly-cloudy-day",
    "2012-02-13": "partly-cloudy-day",
    "2012-02-17": "rain",
    "2012-02-18": "partly-cloudy-day",
    "2012-02-19": "rain",
    "2012-02-20": "partly-cloudy-day",
    "2012-02-24": "rain",
    "2012-02-25": "partly-cloudy-day",
    "2012-02-26": "partly-cloudy-day",
    "2012-02-27": "rain",
    "2012-03-02": "partly-cloudy-day",
    "2012-03-03": "Clear throughout the day.",
    "2012-03-04": "Clear throughout the day.",
    "2012-03-05": "Clear throughout the day.",
    "2012-03-09": "partly-cloudy-day",
    "2012-03-10": "partly-cloudy-day",
    "2012-03-11": "partly-cloudy-day",
    "2012-03-12": "rain",
    "2012-03-13": "partly-cloudy-day",
    "2012-03-14": "partly-cloudy-day",
    "2012-03-16": "Clear throughout the day.",
    "2012-03-17": "Clear throughout the day.",
    "2012-03-18": "partly-cloudy-day",
    "2012-03-19": "partly-cloudy-day",
    "2012-03-20": "partly-cloudy-day",
    "2012-03-21": "partly-cloudy-day",
    "2012-03-23": "clear-day",
    "2012-03-24": "Clear throughout the day.",
    "2012-03-25": "partly-cloudy-day",
    "2012-03-26": "Foggy in the morning.",
    "2012-03-30": "partly-cloudy-day",
    "2012-03-31": "rain",
    "2012-04-01": "partly-cloudy-day",
    "2012-04-02": "rain",
    "2012-04-05": "partly-cloudy-day",
    "2012-04-06": "partly-cloudy-day",
    "2012-04-07": "partly-cloudy-day",
    "2012-04-08": "Clear throughout the day.",
    "2012-04-09": "Clear throughout the day.",
    "2012-04-10": "partly-cloudy-day",
    "2012-04-11": "partly-cloudy-day",
    "2012-04-13": "partly-cloudy-day",
    "2012-04-14": "Partly cloudy throughout the day.",
    "2012-04-15": "partly-cloudy-day",
    "2012-04-16": "Clear throughout the day.",
    "2012-04-20": "Mostly cloudy throughout the day.",
    "2012-04-21": "partly-cloudy-day",
    "2012-04-22": "partly-cloudy-day",
    "2012-04-23": "Partly cloudy throughout the day.",
    "2012-04-24": "rain",
    "2012-04-28": "Clear throughout the day.",
    "2012-04-29": "Clear throughout the day.",
    "2012-04-30": "Clear throughout the day.",
    "2012-05-01": "Clear throughout the day.",
    "2012-05-02": "Clear throughout the day.",
    "2012-05-05": "rain",
    "2012-05-06": "rain",
    "2012-05-07": "partly-cloudy-day",
    "2012-05-08": "partly-cloudy-day",
    "2012-05-13": "partly-cloudy-day"
}